module_b6.py
beishan/__init__.py
beishan/module_b1.py
beishan/module_b2.py
beishan/beishan2/__init__.py
beishan/beishan2/module_b5.py
beishan1/__init__.py
beishan1/module_b3.py
beishan1/module_b4.py
bsmodule-2.1.dist-info/METADATA
bsmodule-2.1.dist-info/WHEEL
bsmodule-2.1.dist-info/top_level.txt
bsmodule-2.1.dist-info/RECORD
