Metadata-Version: 2.1
Name: bsmodule
Version: 2.1
Summary: 这是模块测试
Author: zhang
Author-email: 123@qq.com
